jp_odesolver-0.0.4.dist-info/licenses/LICENSE
odesolver/__init__.py
odesolver/ode.py
odesolver/odesolver.py
odesolver/plotter.py
odesolver/solver.py
jp_odesolver-0.0.4.dist-info/METADATA
jp_odesolver-0.0.4.dist-info/WHEEL
jp_odesolver-0.0.4.dist-info/top_level.txt
jp_odesolver-0.0.4.dist-info/RECORD
